<?xml version="1.0" encoding="UTF-8"?>
<DEFECTS>
  <DEFECT>
    <SFA>
      <FILEPATH>C:\!PROG2\с++ prac\</FILEPATH>
      <FILENAME>Inheritance_Array_empty.cpp</FILENAME>
      <LINE>48</LINE>
      <COLUMN>16</COLUMN>
    </SFA>
    <DEFECTCODE>6386</DEFECTCODE>
    <DESCRIPTION>Buffer overrun while writing to 'this-&gt;ptr'.</DESCRIPTION>
    <FUNCTION>MyArrayParent::{ctor}</FUNCTION>
    <DECORATED>??0MyArrayParent@@QEAA@AEBV0@@Z</DECORATED>
    <FUNCLINE>41</FUNCLINE>
    <PROBABILITY>1</PROBABILITY>
    <RANK>4</RANK>
    <CATEGORY>
      <RULECATEGORY>mspft</RULECATEGORY>
    </CATEGORY>
    <PATH>
      <SFA>
        <FILEPATH>C:\!PROG2\с++ prac\</FILEPATH>
        <FILENAME>Inheritance_Array_empty.cpp</FILENAME>
        <LINE>43</LINE>
        <COLUMN>7</COLUMN>
      </SFA>
      <SFA>
        <FILEPATH>C:\!PROG2\с++ prac\</FILEPATH>
        <FILENAME>Inheritance_Array_empty.cpp</FILENAME>
        <LINE>44</LINE>
        <COLUMN>14</COLUMN>
      </SFA>
      <SFA>
        <FILEPATH>C:\!PROG2\с++ prac\</FILEPATH>
        <FILENAME>Inheritance_Array_empty.cpp</FILENAME>
        <LINE>45</LINE>
        <COLUMN>17</COLUMN>
      </SFA>
      <SFA>
        <FILEPATH>C:\!PROG2\с++ prac\</FILEPATH>
        <FILENAME>Inheritance_Array_empty.cpp</FILENAME>
        <LINE>46</LINE>
        <COLUMN>12</COLUMN>
      </SFA>
      <SFA>
        <FILEPATH>C:\!PROG2\с++ prac\</FILEPATH>
        <FILENAME>Inheritance_Array_empty.cpp</FILENAME>
        <LINE>47</LINE>
        <COLUMN>11</COLUMN>
      </SFA>
      <SFA>
        <FILEPATH>C:\!PROG2\с++ prac\</FILEPATH>
        <FILENAME>Inheritance_Array_empty.cpp</FILENAME>
        <LINE>47</LINE>
        <COLUMN>20</COLUMN>
        <KEYEVENT>
          <ID>1</ID>
          <KIND>branch</KIND>
          <IMPORTANCE>Full</IMPORTANCE>
          <MESSAGE>Enter this loop, (assume 'i&lt;count')</MESSAGE>
        </KEYEVENT>
      </SFA>
      <SFA>
        <FILEPATH>C:\!PROG2\с++ prac\</FILEPATH>
        <FILENAME>Inheritance_Array_empty.cpp</FILENAME>
        <LINE>48</LINE>
        <COLUMN>16</COLUMN>
      </SFA>
      <SFA>
        <FILEPATH>C:\!PROG2\с++ prac\</FILEPATH>
        <FILENAME>Inheritance_Array_empty.cpp</FILENAME>
        <LINE>47</LINE>
        <COLUMN>30</COLUMN>
        <KEYEVENT>
          <ID>2</ID>
          <KIND>declaration</KIND>
          <IMPORTANCE>Essential</IMPORTANCE>
          <MESSAGE>'i' may equal 1</MESSAGE>
        </KEYEVENT>
      </SFA>
      <SFA>
        <FILEPATH>C:\!PROG2\с++ prac\</FILEPATH>
        <FILENAME>Inheritance_Array_empty.cpp</FILENAME>
        <LINE>47</LINE>
        <COLUMN>20</COLUMN>
        <KEYEVENT>
          <ID>3</ID>
          <KIND>branch</KIND>
          <IMPORTANCE>Full</IMPORTANCE>
          <MESSAGE>Continue this loop, (assume 'i&lt;count')</MESSAGE>
        </KEYEVENT>
      </SFA>
      <SFA>
        <FILEPATH>C:\!PROG2\с++ prac\</FILEPATH>
        <FILENAME>Inheritance_Array_empty.cpp</FILENAME>
        <LINE>48</LINE>
        <COLUMN>16</COLUMN>
        <KEYEVENT>
          <ID>4</ID>
          <KIND>usage</KIND>
          <IMPORTANCE>Essential</IMPORTANCE>
          <MESSAGE>Invalid write to 'this-&gt;ptr[1]', (writable range is 0 to 0)</MESSAGE>
        </KEYEVENT>
      </SFA>
    </PATH>
  </DEFECT>
  <DEFECT>
    <SFA>
      <FILEPATH>C:\!PROG2\с++ prac\</FILEPATH>
      <FILENAME>Inheritance_Array_empty.cpp</FILENAME>
      <LINE>121</LINE>
      <COLUMN>17</COLUMN>
    </SFA>
    <DEFECTCODE>6386</DEFECTCODE>
    <DESCRIPTION>Buffer overrun while writing to 'ptr'.</DESCRIPTION>
    <FUNCTION>MyArrayParent::push</FUNCTION>
    <DECORATED>?push@MyArrayParent@@QEAAXN@Z</DECORATED>
    <FUNCLINE>99</FUNCLINE>
    <PROBABILITY>1</PROBABILITY>
    <RANK>4</RANK>
    <CATEGORY>
      <RULECATEGORY>mspft</RULECATEGORY>
    </CATEGORY>
    <PATH>
      <SFA>
        <FILEPATH>C:\!PROG2\с++ prac\</FILEPATH>
        <FILENAME>Inheritance_Array_empty.cpp</FILENAME>
        <LINE>101</LINE>
        <COLUMN>12</COLUMN>
        <KEYEVENT>
          <ID>1</ID>
          <KIND>branch</KIND>
          <IMPORTANCE>Full</IMPORTANCE>
          <MESSAGE>Skip this branch, (assume 'count&lt;capacity' is false)</MESSAGE>
        </KEYEVENT>
      </SFA>
      <SFA>
        <FILEPATH>C:\!PROG2\с++ prac\</FILEPATH>
        <FILENAME>Inheritance_Array_empty.cpp</FILENAME>
        <LINE>109</LINE>
        <COLUMN>11</COLUMN>
      </SFA>
      <SFA>
        <FILEPATH>C:\!PROG2\с++ prac\</FILEPATH>
        <FILENAME>Inheritance_Array_empty.cpp</FILENAME>
        <LINE>110</LINE>
        <COLUMN>8</COLUMN>
      </SFA>
      <SFA>
        <FILEPATH>C:\!PROG2\с++ prac\</FILEPATH>
        <FILENAME>Inheritance_Array_empty.cpp</FILENAME>
        <LINE>111</LINE>
        <COLUMN>11</COLUMN>
        <KEYEVENT>
          <ID>2</ID>
          <KIND>declaration</KIND>
          <IMPORTANCE>Essential</IMPORTANCE>
          <MESSAGE>'capacity' may equal 1</MESSAGE>
        </KEYEVENT>
      </SFA>
      <SFA>
        <FILEPATH>C:\!PROG2\с++ prac\</FILEPATH>
        <FILENAME>Inheritance_Array_empty.cpp</FILENAME>
        <LINE>113</LINE>
        <COLUMN>12</COLUMN>
      </SFA>
      <SFA>
        <FILEPATH>C:\!PROG2\с++ prac\</FILEPATH>
        <FILENAME>Inheritance_Array_empty.cpp</FILENAME>
        <LINE>113</LINE>
        <COLUMN>21</COLUMN>
        <KEYEVENT>
          <ID>3</ID>
          <KIND>branch</KIND>
          <IMPORTANCE>Full</IMPORTANCE>
          <MESSAGE>Skip this loop, (assume 'i&lt;capacity-1' is false)</MESSAGE>
        </KEYEVENT>
      </SFA>
      <SFA>
        <FILEPATH>C:\!PROG2\с++ prac\</FILEPATH>
        <FILENAME>Inheritance_Array_empty.cpp</FILENAME>
        <LINE>118</LINE>
        <COLUMN>3</COLUMN>
      </SFA>
      <SFA>
        <FILEPATH>C:\!PROG2\с++ prac\</FILEPATH>
        <FILENAME>Inheritance_Array_empty.cpp</FILENAME>
        <LINE>119</LINE>
        <COLUMN>7</COLUMN>
      </SFA>
      <SFA>
        <FILEPATH>C:\!PROG2\с++ prac\</FILEPATH>
        <FILENAME>Inheritance_Array_empty.cpp</FILENAME>
        <LINE>121</LINE>
        <COLUMN>17</COLUMN>
        <KEYEVENT>
          <ID>4</ID>
          <KIND>usage</KIND>
          <IMPORTANCE>Essential</IMPORTANCE>
          <MESSAGE>Invalid write to 'ptr[1]', (writable range is 0 to 0)</MESSAGE>
        </KEYEVENT>
      </SFA>
    </PATH>
  </DEFECT>
</DEFECTS>